witter/__init__.py
witter/__main__.py
witter/chain_generator.py
witter-0.0.8.dist-info/METADATA
witter-0.0.8.dist-info/WHEEL
witter-0.0.8.dist-info/entry_points.txt
witter-0.0.8.dist-info/RECORD
