Metadata-Version: 2.1
Name: witter
Version: 0.0.8
Summary: Witter - generate random text in the style of the document you provide.
License: Apache-2.0
Keywords: text,generator,ml,statistics,random
Author: Jason Ross (big-jr)
Author-email: jason@softwarepragmatism.com
Maintainer: Jason Ross (big-jr)
Maintainer-email: jason@softwarepragmatism.com
Requires-Python: >=3.9,<4.0
Classifier: Development Status :: 2 - Pre-Alpha
Classifier: Environment :: Console
Classifier: License :: OSI Approved :: Apache Software License
Classifier: Operating System :: OS Independent
Classifier: Programming Language :: Python :: 3
Classifier: Programming Language :: Python :: 3.9
Classifier: Programming Language :: Python :: 3.10
Classifier: Programming Language :: Python :: 3.11
Classifier: Programming Language :: Python :: 3.12
